mailmanclient/__init__.py
mailmanclient/_client.py
mailmanclient/client.py
mailmanclient/conftest.py
mailmanclient/constants.py
mailmanclient/docs/NEWS.rst
mailmanclient/docs/__init__.py
mailmanclient/docs/apiref.rst
mailmanclient/docs/conftest.py
mailmanclient/docs/testing.rst
mailmanclient/docs/using.rst
mailmanclient/restbase/__init__.py
mailmanclient/restbase/base.py
mailmanclient/restbase/connection.py
mailmanclient/restbase/page.py
mailmanclient/restobjects/__init__.py
mailmanclient/restobjects/address.py
mailmanclient/restobjects/archivers.py
mailmanclient/restobjects/ban.py
mailmanclient/restobjects/configuration.py
mailmanclient/restobjects/domain.py
mailmanclient/restobjects/header_match.py
mailmanclient/restobjects/held_message.py
mailmanclient/restobjects/mailinglist.py
mailmanclient/restobjects/member.py
mailmanclient/restobjects/preferences.py
mailmanclient/restobjects/queue.py
mailmanclient/restobjects/settings.py
mailmanclient/restobjects/styles.py
mailmanclient/restobjects/templates.py
mailmanclient/restobjects/user.py
mailmanclient/testing/__init__.py
mailmanclient/testing/documentation.py
mailmanclient/testing/vcr_helpers.py
mailmanclient/tests/__init__.py
mailmanclient/tests/test_client.py
mailmanclient/tests/test_domain.py
mailmanclient/tests/test_list.py
mailmanclient/tests/test_page.py
mailmanclient/tests/test_templates.py
mailmanclient/tests/test_unicode.py
mailmanclient/tests/data/TestDomains.test_no_domain.yaml
mailmanclient/tests/data/TestMailingListMembershipTests.test_list_is_member.yaml
mailmanclient/tests/data/TestMailingListMembershipTests.test_list_is_moderator.yaml
mailmanclient/tests/data/TestMailingListMembershipTests.test_list_is_owner.yaml
mailmanclient/tests/data/TestMailingListMembershipTests.test_list_is_owner_or_mod.yaml
mailmanclient/tests/data/TestTemplates.test_domain_templates_with_password.yaml
mailmanclient/tests/data/TestTemplates.test_list_templates_with_password.yaml
mailmanclient-3.3.0.dist-info/COPYING.LESSER
mailmanclient-3.3.0.dist-info/METADATA
mailmanclient-3.3.0.dist-info/WHEEL
mailmanclient-3.3.0.dist-info/top_level.txt
mailmanclient-3.3.0.dist-info/RECORD
