Metadata-Version: 2.1
Name: mailmanclient
Version: 3.3.0
Summary: mailmanclient -- Python bindings for Mailman REST API
Home-page: http://www.list.org/
Maintainer: Barry Warsaw
Maintainer-email: barry@list.org
License: LGPLv3
Platform: UNKNOWN
Classifier: License :: OSI Approved :: GNU General Public License v3 or later (GPLv3+)
Classifier: Operating System :: POSIX
Classifier: Programming Language :: Python :: 3.5
Classifier: Programming Language :: Python :: 3.6
Classifier: Programming Language :: Python :: 3.7
Classifier: Topic :: Internet :: WWW/HTTP 
Requires-Dist: requests
Provides-Extra: lint
Requires-Dist: flake8 (>3.0) ; extra == 'lint'
Provides-Extra: testing
Requires-Dist: pytest ; extra == 'testing'
Requires-Dist: pytest-vcr ; extra == 'testing'
Requires-Dist: pytest-services ; extra == 'testing'
Requires-Dist: mailman ; extra == 'testing'
Requires-Dist: falcon (==1.4.1) ; extra == 'testing'
